CHANGELOG.txt
LICENCE.txt
MANIFEST.in
README.rst
pyproject.toml
setup.py
temp.txt
template.txt
toot.txt
tweet.txt
.tx/config
src/doc/api_index.rst
src/doc/conf.py
src/doc/copyright.rst
src/doc/img_1504.jpg
src/doc/index.rst
src/doc/pywws_logo.ico
src/doc/pywws_logo.png
src/doc/requirements.txt
src/doc/essentials/CHANGELOG.rst
src/doc/essentials/LICENCE.rst
src/doc/essentials/dependencies.rst
src/doc/guides/getstarted.rst
src/doc/guides/hourlylogging.rst
src/doc/guides/humidex.rst
src/doc/guides/index.rst
src/doc/guides/integration.rst
src/doc/guides/language.rst
src/doc/guides/livelogging.rst
src/doc/guides/logfiles.rst
src/doc/guides/weather_ini.rst
src/pywws/__init__.py
src/pywws/calib.py
src/pywws/constants.py
src/pywws/conversions.py
src/pywws/datastoretransfer.py
src/pywws/device_ctypes_hidapi.py
src/pywws/device_cython_hidapi.py
src/pywws/device_libusb1.py
src/pywws/device_pyusb.py
src/pywws/device_pyusb1.py
src/pywws/filedata.py
src/pywws/forecast.py
src/pywws/hourly.py
src/pywws/livelog.py
src/pywws/livelogdaemon.py
src/pywws/localisation.py
src/pywws/logdata.py
src/pywws/logger.py
src/pywws/mergeewdata.py
src/pywws/plot.py
src/pywws/process.py
src/pywws/regulartasks.py
src/pywws/reprocess.py
src/pywws/setweatherstation.py
src/pywws/sqlite3data.py
src/pywws/storage.py
src/pywws/template.py
src/pywws/testweatherstation.py
src/pywws/timezone.py
src/pywws/usbtest.py
src/pywws/version.py
src/pywws/weatherstation.py
src/pywws/windrose.py
src/pywws.egg-info/PKG-INFO
src/pywws.egg-info/SOURCES.txt
src/pywws.egg-info/dependency_links.txt
src/pywws.egg-info/entry_points.txt
src/pywws.egg-info/not-zip-safe
src/pywws.egg-info/requires.txt
src/pywws.egg-info/top_level.txt
src/pywws/examples/graph_templates/2008.png.xml
src/pywws/examples/graph_templates/2009.png.xml
src/pywws/examples/graph_templates/2016candle.png.xml
src/pywws/examples/graph_templates/24hrs.png.xml
src/pywws/examples/graph_templates/24hrs_average_winddir.png.xml
src/pywws/examples/graph_templates/24hrs_full_features.png.xml
src/pywws/examples/graph_templates/28days.png.xml
src/pywws/examples/graph_templates/7days.png.xml
src/pywws/examples/graph_templates/Oct_08.png.xml
src/pywws/examples/graph_templates/humidex.png.xml
