Metadata-Version: 2.4
Name: pywws
Version: 25.10.0
Summary: Python software for wireless weather stations
Author: pywws contributors
Author-email: Jim Easterbrook <jim@jim-easterbrook.me.uk>
License: GPLv2+
Project-URL: Homepage, https://github.com/jim-easterbrook/pywws/
Classifier: Development Status :: 6 - Mature
Classifier: Intended Audience :: End Users/Desktop
Classifier: License :: OSI Approved :: GNU General Public License v2 (GPLv2)
Classifier: Operating System :: OS Independent
Classifier: Programming Language :: Python
Classifier: Programming Language :: Python :: 2.7
Classifier: Programming Language :: Python :: 3
License-File: LICENCE.txt
Requires-Dist: python-dateutil
Provides-Extra: daemon
Requires-Dist: python-daemon==2.1.2; extra == "daemon"
Provides-Extra: sftp
Requires-Dist: paramiko; extra == "sftp"
Requires-Dist: pycrypto; extra == "sftp"
Provides-Extra: twitter
Requires-Dist: python-twitter>=3.0; extra == "twitter"
Requires-Dist: oauth2; extra == "twitter"
Dynamic: license-file
